{
  "patterns": {
    "A_number_hook": {
      "label": "数字フック",
      "regime": "risk_on",
      "body": "【明日上がる日本株】\nプライム{universe_size}銘柄スキャン → スコア{score}点\n\n{name}（{ticker_display}）\n\n{reason_1}\n{reason_2}\n{reason_3}\n\nレジーム: リスクオン\n保有想定: {holding_window}\n\n#因果律 #日本株 #クオンツ",
      "self_reply": "律は毎日数字だけで判断してます。気になる人はフォローしてください。"
    },
    "D_warning": {
      "label": "警告型",
      "regime": "risk_off",
      "body": "【因果律】今日はノートレード。\n\nレジームがリスクオフ。律のルールでは無理に出しません。\n休むのも戦略です。\n\n#因果律 #日本株",
      "self_reply": ""
    },
    "F_provoke": {
      "label": "挑発型",
      "regime": "risk_on",
      "body": "まだ勘で銘柄選んでますか？\n\n律はプライム{universe_size}銘柄を毎日スキャン。\n今日のトップ → {name}（{ticker_display}）スコア{score}\n\n{reason_1}\n{reason_2}\n{reason_3}\n\n感覚より数字。\n\n#因果律 #日本株 #AI投資",
      "self_reply": "保有想定は{holding_window}。レジームはリスクオン。律のシグナル、毎日出してます。"
    }
  },
  "selection_rule": {
    "risk_on": ["A_number_hook", "F_provoke"],
    "risk_off": ["D_warning"],
    "rotation": "alternate"
  }
}
